[
  {"model": "auth.user",
    "pk": 1, 
    "fields": 
      {
       "password": "pbkdf2_sha256$260000$amHGxdj2lwbKFQfFqEPTPb$h54VVeP6A0P1nnBuX/T4xEmA6x6bOXRa/yEV5cycl+0=", 
       "last_login": "2021-09-29T08:50:44.236Z",
       "is_superuser": true,
       "username": "admin",
       "first_name": "",
       "last_name": "",
       "email": "",
       "is_staff": true,
       "is_active": true,
       "date_joined": "2021-09-18T08:31:05.866Z",
       "groups": [],
       "user_permissions": []
      }
  },
    {
      "model": "myapp.employee",
      "pk": 1,
      "fields": {
        "user": "1"
      }
    },
    {
      "model": "myapp.item",
      "pk": 1,
      "fields": {
        "name": "Banana",
        "employe": "1",
        "price": "40.00"
      }
    },
    {
      "model": "myapp.sale",
      "pk": 1,
      "fields": {
        "item": "1",
        "employe": "1",
        "count": "1",
        "total_price": "40.00",
        "price_one_item": "40.00",
        "date_sale": "2021-09-17"
      }
    },
    {
      "model": "myapp.changeprice",
      "pk": 1,
      "fields": {
        "item": "1",
        "price": "40.00",
        "date_change": "2021-09-17"
      }
    }
  ]